[
  {"nombre": "VAN AERT Wout", "equipo": "JUMBO-VISMA", "puntos":150}, 
  {"nombre": "POGAČAR Tadej", "equipo": "UAE TEAM EMIRATES", "puntos":123}, 
  {"nombre": "VAN DER POEL Mathieu", "equipo": "ALPECIN-FENIX", "puntos":108}, 
  {"nombre": "YATES Adam", "equipo": "INEOS GRENADIERS", "puntos":99}, 
  {"nombre": "ALMEIDA João", "equipo": "DECEUNINCK - QUICK-STEP", "puntos":71}, 
  {"nombre": "BERNAL Egan", "equipo": "INEOS GRENADIERS", "puntos":55}, 
  {"nombre": "SCHACHMANN Maximilian", "equipo": "BORA - HANSGROHE", "puntos":54}, 
  {"nombre": "BENNETT Sam", "equipo": "DECEUNINCK - QUICK-STEP", "puntos":53}, 
  {"nombre": "STUYVEN Jasper", "equipo": "TREK - SEGAFREDO", "puntos":51}, 
  {"nombre": "EWAN Caleb", "equipo": "LOTTO SOUDAL", "puntos":49}, 
  {"nombre": "NIZZOLO Giacomo", "equipo": "equipo QHUBEKA ASSOS", "puntos":44}, 
  {"nombre": "TRENTIN Matteo", "equipo": "UAE TEAM EMIRATES", "puntos":44}, 
  {"nombre": "VAN BAARLE Dylan", "equipo": "INEOS GRENADIERS", "puntos":42}, 
  {"nombre": "VLASOV Aleksandr", "equipo": "ASTANA - PREMIER TECH", "puntos":40}, 
  {"nombre": "ASGREEN Kasper", "equipo": "DECEUNINCK - QUICK-STEP", "puntos":40}, 
  {"nombre": "SÉNÉCHAL Florian", "equipo": "DECEUNINCK - QUICK-STEP", "puntos":40}, 
  {"nombre": "PORTE Richie", "equipo": "INEOS GRENADIERS", "puntos":40}, 
  {"nombre": "COLBRELLI Sonny", "equipo": "BAHRAIN VICTORIOUS", "puntos":39}, 
  {"nombre": "MATTHEWS Michael", "equipo": "equipo BIKEEXCHANGE", "puntos":37}, 
  {"nombre": "THOMAS Geraint", "equipo": "INEOS GRENADIERS", "puntos":36}, 
  {"nombre": "IZAGIRRE Ion", "equipo": "ASTANA - PREMIER TECH", "puntos":35}, 
  {"nombre": "LANDA Mikel", "equipo": "BAHRAIN VICTORIOUS", "puntos":35}, 
  {"nombre": "SAGAN Peter", "equipo": "BORA - HANSGROHE", "puntos":35}, 
  {"nombre": "ALAPHILIPPE Julian", "equipo": "DECEUNINCK - QUICK-STEP", "puntos":35}, 
  {"nombre": "PEDERSEN Mads", "equipo": "TREK - SEGAFREDO", "puntos":34}, 
  {"nombre": "PIDCOCK Thomas", "equipo": "INEOS GRENADIERS", "puntos":33}, 
  {"nombre": "TURGIS Anthony", "equipo": "TOTAL DIRECT ENERGIE", "puntos":33}, 
  {"nombre": "HAMILTON Lucas", "equipo": "equipo BIKEEXCHANGE", "puntos":32}, 
  {"nombre": "BALLERINI Davide", "equipo": "DECEUNINCK - QUICK-STEP", "puntos":31}, 
  {"nombre": "VALVERDE Alejandro", "equipo": "MOVISTAR TEAM", "puntos":31}
  ]